{
    "_default": {
        "1": {
            "dyttid": "59496",
            "stat_down": 2,
            "name_chn": [
                "\u5929\u4f5c\u8c1c\u6848",
                "\u5929\u4f5c\u51f6\u6740\u6848",
                "\u65e0\u5de7\u4e0d\u6210\u4e66"
            ],
            "name": [
                "Ittefaq",
                "Coincidence"
            ],
            "year": 2017,
            "magnet": "magnet:?xt=urn:btih:fddd40d4973cc4350bd09745ba6f85b4615a9208",
            "downlink": "ftp://ygdy8:ygdy8@yg49.dydytt.net:3001/\u9633\u5149\u7535\u5f71www.ygdy8.com.\u5929\u4f5c\u8c1c\u6848.BD.1080p.\u56fd\u5370\u53cc\u8bed\u4e2d\u5b57.mkv",
            "name_folder": "Ittefaq(2017)"
        },
        "2": {
            "dyttid": "59495",
            "stat_down": 2,
            "name_chn": [
                "\u6469\u6bd4\u5c0f\u5b50\u5927\u7535\u5f71",
                "\u6469\u6bd4\u4e16\u754c",
                "\u767e\u4e50\u5b9d\u5927\u7535\u5f71"
            ],
            "name": [
                "Playmobil: the Movie",
                "Playmobil: Robbers, Thieves &amp; Rebels"
            ],
            "year": 2019,
            "magnet": "magnet:?xt=urn:btih:b491b0d22f206716b708e1100d3710916d2712d2",
            "downlink": "ftp://ygdy8:ygdy8@yg39.dydytt.net:7002/\u9633\u5149\u7535\u5f71www.ygdy8.com.\u6469\u6bd4\u5c0f\u5b50\u5927\u7535\u5f71.BD.1080p.\u4e2d\u82f1\u53cc\u5b57\u5e55.mkv",
            "name_folder": "Playmobil__the_Movie(2019)"
        },
        "3": {
            "dyttid": "59491",
            "stat_down": 2,
            "name_chn": [
                "\u5362\u65af",
                "\u5362\u65af\u7684\u79d8\u5bc6(\u6e2f)"
            ],
            "name": [
                "Luce"
            ],
            "year": 2019,
            "magnet": "magnet:?xt=urn:btih:e7b8ea59d63406f27c8da76d11196d1d701aea61",
            "downlink": "ftp://ygdy8:ygdy8@yg45.dydytt.net:6193/\u9633\u5149\u7535\u5f71www.ygdy8.com.\u5362\u65af\u7684\u79d8\u5bc6.BD.1080p.\u4e2d\u82f1\u53cc\u5b57\u5e55.mkv",
            "name_folder": "Luce(2019)"
        },
        "4": {
            "dyttid": "59489",
            "stat_down": 2,
            "name_chn": [
                "\u6218\u80dc\u81ea\u6211"
            ],
            "name": [
                "Overcomer"
            ],
            "year": 2019,
            "magnet": "magnet:?xt=urn:btih:5f393283ab08e52ef7f39f93933d9e5fe12d1e27",
            "downlink": "ftp://ygdy8:ygdy8@yg49.dydytt.net:7001/\u9633\u5149\u7535\u5f71www.ygdy8.com.\u6218\u80dc\u81ea\u6211.BD.1080p.\u82f1\u8bed\u4e2d\u5b57.mkv",
            "name_folder": "Overcomer(2019)"
        },
        "5": {
            "dyttid": "59474",
            "stat_down": 1,
            "name_chn": [
                "\u5a5a\u59fb\u6545\u4e8b"
            ],
            "name": [
                "Marriage Story"
            ],
            "year": 2019,
            "magnet": "magnet:?xt=urn:btih:7ceb59285bde69d587bccdde5177c3ad54955b0d",
            "downlink": "ftp://ygdy8:ygdy8@yg45.dydytt.net:4234/\u9633\u5149\u7535\u5f71www.ygdy8.com.\u5a5a\u59fb\u6545\u4e8b.BD.1080p.\u4e2d\u82f1\u53cc\u5b57\u5e55.mkv",
            "name_folder": "Marriage_Story(2019)"
        },
        "6": {
            "dyttid": "59466",
            "stat_down": 2,
            "name_chn": [
                "\u9177\u5211\u62a5\u544a"
            ],
            "name": [
                "The Report",
                "Ancient of Days",
                "The Torture Report"
            ],
            "year": 2019,
            "magnet": "magnet:?xt=urn:btih:914625c5137e79f652dc8937f558b80816b35433",
            "downlink": "ftp://ygdy8:ygdy8@yg68.dydytt.net:8037/\u9633\u5149\u7535\u5f71www.ygdy8.com.\u9177\u5211\u62a5\u544a.BD.1080p.\u4e2d\u82f1\u53cc\u5b57\u5e55.mkv",
            "name_folder": "The_Report(2019)"
        },
        "7": {
            "dyttid": "59465",
            "stat_down": 2,
            "name_chn": [
                "\u8fbe\u4ee4\u4e4b\u7f6a",
                "\u4eb2\u7231\u7684",
                "\u8fbe\u7433"
            ],
            "name": [
                "Darlin'"
            ],
            "year": 2019,
            "magnet": "magnet:?xt=urn:btih:adfd7de3f331dc31dc7aea149cfecc0df4f72f56",
            "downlink": "ftp://ygdy8:ygdy8@yg45.dydytt.net:7537/\u9633\u5149\u7535\u5f71www.ygdy8.com.\u8fbe\u4ee4\u4e4b\u7f6a.BD.1080p.\u4e2d\u82f1\u53cc\u5b57\u5e55.mkv",
            "name_folder": "Darlin'(2019)"
        },
        "8": {
            "dyttid": "59464",
            "stat_down": 2,
            "name_chn": [
                "\u5341\u5b57\u8ffd\u6740\u4ee43"
            ],
            "name": [
                "Cross 3"
            ],
            "year": 2019,
            "magnet": "magnet:?xt=urn:btih:4b3e24836d22b03302ab016aafea5506a5dd6e35",
            "downlink": "ftp://ygdy8:ygdy8@yg49.dydytt.net:8001/\u9633\u5149\u7535\u5f71www.ygdy8.com.\u5341\u5b57\u8ffd\u6740\u4ee43.BD.1080p.\u4e2d\u82f1\u53cc\u5b57\u5e55.mkv",
            "name_folder": "Cross_3(2019)"
        },
        "9": {
            "dyttid": "59463",
            "stat_down": 2,
            "name_chn": [
                "\u602a\u80ce"
            ],
            "name": [
                "Freaks"
            ],
            "year": 2018,
            "magnet": "magnet:?xt=urn:btih:6d9407bb384c6882c908cd92ff0bf11169997ae7",
            "downlink": "ftp://ygdy8:ygdy8@yg49.dydytt.net:7001/\u9633\u5149\u7535\u5f71www.ygdy8.com.\u602a\u80ce.BD.1080p.\u4e2d\u82f1\u53cc\u5b57\u5e55.mkv",
            "name_folder": "Freaks(2018)"
        },
        "10": {
            "dyttid": "59458",
            "stat_down": 2,
            "name_chn": [
                "\u661f\u9645\u63a2\u7d22",
                "\u661f\u9645\u4efb\u52a1(\u6e2f)",
                "\u661f\u9645\u63a2\u9669",
                "\u661f\u9645\u6551\u63f4(\u53f0)"
            ],
            "name": [
                "Ad Astra"
            ],
            "year": 2019,
            "magnet": "magnet:?xt=urn:btih:f294325fd7dc7a20fa278d6ab5e5f74a4a1bcb2f",
            "downlink": "ftp://ygdy8:ygdy8@yg45.dydytt.net:3245/\u9633\u5149\u7535\u5f71www.ygdy8.com.\u661f\u9645\u6551\u63f4.HD.1080p.\u4e2d\u82f1\u53cc\u5b57\u5e55.mkv",
            "name_folder": "Ad_Astra(2019)"
        },
        "11": {
            "dyttid": "59494",
            "stat_down": 2,
            "name": [
                "\u6bd2\u6218\u751f\u6b7b\u7ebf"
            ],
            "year": 2019,
            "magnet": "magnet:?xt=urn:btih:80d4e70d21f1eb716e7cd472efc84cec4ef6a31a",
            "downlink": "ftp://ygdy8:ygdy8@yg45.dydytt.net:3246/\u9633\u5149\u7535\u5f71www.ygdy8.com.\u6bd2\u6218\u751f\u6b7b\u7ebf.HD.1080p.\u56fd\u8bed\u4e2d\u5b57.mp4",
            "name_folder": "\u6bd2\u6218\u751f\u6b7b\u7ebf(2019)"
        },
        "12": {
            "dyttid": "59490",
            "stat_down": 2,
            "name_chn": [
                "\u8ffd\u51f6\u5341\u4e5d\u5e74",
                "\u4e0d\u53ef\u6740\u622e"
            ],
            "name": [
                "Bloody Daisy"
            ],
            "year": 2019,
            "magnet": "magnet:?xt=urn:btih:c989a167a79530f060f141a3b0a6b6b1b5a3a8a5",
            "downlink": "ftp://ygdy8:ygdy8@yg39.dydytt.net:3001/\u9633\u5149\u7535\u5f71www.ygdy8.com.\u8ffd\u51f6\u5341\u4e5d\u5e74.HD.1080p.\u56fd\u8bed\u4e2d\u5b57.mp4",
            "name_folder": "Bloody_Daisy(2019)"
        },
        "13": {
            "dyttid": "59475",
            "stat_down": 1,
            "name_chn": [
                "\u50ac\u7720\u00b7\u88c1\u51b3",
                "\u50ac\u7720\u88c1Q"
            ],
            "name": [
                "Guilt by Design",
                "Hypnotize the Jury"
            ],
            "year": 2019,
            "magnet": "magnet:?xt=urn:btih:d70ef3465d11160d3f7b4639d5b1f6230e78d508",
            "downlink": "ftp://ygdy8:ygdy8@yg49.dydytt.net:6001/\u9633\u5149\u7535\u5f71www.ygdy8.com.\u50ac\u7720\u30fb\u88c1\u51b3.HD.2160p.\u56fd\u7ca4\u53cc\u8bed\u4e2d\u5b57.mkv",
            "name_folder": "Guilt_by_Design(2019)"
        },
        "14": {
            "dyttid": "59453",
            "stat_down": 2,
            "name_chn": [
                "\u4e2d\u56fd\u673a\u957f"
            ],
            "name": [
                "The Captain",
                "The Chinese Pilot"
            ],
            "year": 2019,
            "magnet": "magnet:?xt=urn:btih:efbdb5ee958e4f097e90a1678ff414faa77eca5d",
            "downlink": "ftp://ygdy8:ygdy8@yg45.dydytt.net:4233/\u9633\u5149\u7535\u5f71www.ygdy8.com.\u4e2d\u56fd\u673a\u957f.HD.1080p.\u56fd\u8bed\u4e2d\u82f1\u53cc\u5b57.mkv",
            "name_folder": "The_Captain(2019)"
        },
        "15": {
            "dyttid": "59444",
            "stat_down": 2,
            "name_chn": [
                "\u4f0f\u5996\u00b7\u767d\u9c7c\u95472 ",
                " \u4f0f\u5996\u00b7\u767d\u9c7c\u9547\u4e4b\u6597\u6cd5\u91d1\u94f6\u697c"
            ],
            "name": [
                "\u4f0f\u5996\u767d\u9c7c\u95472"
            ],
            "year": 2019,
            "magnet": "magnet:?xt=urn:btih:0b4179c1ed5552f3bb1e70b502db9d6b7a79259b",
            "downlink": "ftp://ygdy8:ygdy8@yg45.dydytt.net:8536/\u9633\u5149\u7535\u5f71www.ygdy8.com.\u4f0f\u5996\u767d\u9c7c\u95472.HD.1080p.\u56fd\u8bed\u4e2d\u5b57.mp4",
            "name_folder": "\u4f0f\u5996\u767d\u9c7c\u95472(2019)"
        },
        "16": {
            "dyttid": "59443",
            "stat_down": 2,
            "name": [
                "\u82f1\u96c4\u65e0\u4fa0"
            ],
            "year": 2019,
            "magnet": "magnet:?xt=urn:btih:b905a1682727a01c8b15b9ca2850b794e96f605c",
            "downlink": "ftp://ygdy8:ygdy8@yg45.dydytt.net:7536/\u9633\u5149\u7535\u5f71www.ygdy8.com.\u82f1\u96c4\u65e0\u4fa0.HD.1080p.\u56fd\u8bed\u4e2d\u5b57.mp4",
            "name_folder": "\u82f1\u96c4\u65e0\u4fa0(2019)"
        },
        "17": {
            "dyttid": "59428",
            "stat_down": 2,
            "name_chn": [
                "\u96ea\u66b4"
            ],
            "name": [
                "Savage"
            ],
            "year": 2018,
            "magnet": "magnet:?xt=urn:btih:37c2ab4d2b0f62bad0f289ef5e023f96ff839cdf",
            "downlink": "ftp://ygdy8:ygdy8@yg45.dydytt.net:5070/\u9633\u5149\u7535\u5f71www.ygdy8.com.\u96ea\u66b4.BD.1080p.\u56fd\u8bed\u4e2d\u5b57.mkv",
            "name_folder": "Savage(2018)"
        },
        "18": {
            "dyttid": "59425",
            "stat_down": 2,
            "name_chn": [
                "\u5c11\u5e74\u7684\u4f60",
                "\u5c11\u5e74\u7684\u4f60\uff0c\u5982\u6b64\u7f8e\u4e3d"
            ],
            "name": [
                "Better Days"
            ],
            "year": 2019,
            "magnet": "magnet:?xt=urn:btih:51b8521967315ad1ea7e62c25d11d616590bb4e7",
            "downlink": "ftp://ygdy8:ygdy8@yg45.dydytt.net:5069/\u9633\u5149\u7535\u5f71www.ygdy8.com.\u5c11\u5e74\u7684\u4f60.HD.1080p.\u56fd\u8bed\u4e2d\u5b57.mkv",
            "name_folder": "Better_Days(2019)"
        },
        "19": {
            "dyttid": "59424",
            "stat_down": 2,
            "name_chn": [
                "\u6500\u767b\u8005"
            ],
            "name": [
                "The Climbers"
            ],
            "year": 2019,
            "magnet": "magnet:?xt=urn:btih:20ccdbe7dbd93a5f6573feb2c5151c25c29fb7f8",
            "downlink": "ftp://ygdy8:ygdy8@yg68.dydytt.net:7032/\u9633\u5149\u7535\u5f71www.ygdy8.com.\u6500\u767b\u8005.HD.1080p.\u56fd\u8bed\u4e2d\u82f1\u53cc\u5b57.mp4",
            "name_folder": "The_Climbers(2019)"
        },
        "20": {
            "dyttid": "59421",
            "stat_down": 2,
            "name_chn": [
                "\u732b\u4e0e\u6843\u82b1\u6e90"
            ],
            "name": [
                "Cats and Peachtopia ",
                " \u732b\u54aa\u5988\u54aaHOME(\u6e2f)"
            ],
            "year": 2018,
            "magnet": "magnet:?xt=urn:btih:af1e9d6ec37457614f65b5591b1fa5b2bab129e6",
            "downlink": "ftp://ygdy8:ygdy8@yg45.dydytt.net:7535/\u9633\u5149\u7535\u5f71www.ygdy8.com.\u732b\u4e0e\u6843\u82b1\u6e90.BD.1080p.\u56fd\u7ca4\u53cc\u8bed\u4e2d\u5b57.mkv",
            "name_folder": "Cats_and_Peachtopia_(2018)"
        }
    }
}